{"stats":{"minecraft:used":{"minecraft:chiseled_stone_bricks":6,"minecraft:anvil":2,"minecraft:cobblestone_stairs":1,"minecraft:gray_carpet":3,"minecraft:andesite":4,"minecraft:light_gray_carpet":45},"minecraft:mined":{"minecraft:grass":1,"minecraft:light_gray_carpet":2},"minecraft:picked_up":{"minecraft:light_gray_carpet":2,"minecraft:nether_star":3},"minecraft:custom":{"minecraft:time_since_rest":42606,"minecraft:crouch_one_cm":561,"minecraft:sprint_one_cm":33715,"minecraft:play_time":42606,"minecraft:open_enderchest":1,"minecraft:walk_one_cm":34167,"minecraft:sneak_time":434,"minecraft:walk_under_water_one_cm":1705,"minecraft:interact_with_anvil":1,"minecraft:jump":204,"minecraft:leave_game":20,"minecraft:walk_on_water_one_cm":264,"minecraft:time_since_death":42606,"minecraft:total_world_time":42606,"minecraft:fall_one_cm":3379,"minecraft:fly_one_cm":157285}},"DataVersion":2975}